dbt/adapters/watsonx_presto/__init__.py
dbt/adapters/watsonx_presto/__version__.py
dbt/adapters/watsonx_presto/column.py
dbt/adapters/watsonx_presto/connections.py
dbt/adapters/watsonx_presto/impl.py
dbt/include/watsonx_presto/__init__.py
dbt/include/watsonx_presto/dbt_project.yml
dbt/include/watsonx_presto/sample_profiles.yml
dbt/include/watsonx_presto/macros/adapters.sql
dbt/include/watsonx_presto/macros/catalog.sql
dbt/include/watsonx_presto/macros/materializations/incremental.sql
dbt/include/watsonx_presto/macros/materializations/snapshot.sql
dbt/include/watsonx_presto/macros/materializations/table.sql
dbt/include/watsonx_presto/macros/materializations/view.sql
dbt_watsonx_presto-0.1.2.dist-info/licenses/LICENSE
dbt_watsonx_presto-0.1.2.dist-info/METADATA
dbt_watsonx_presto-0.1.2.dist-info/WHEEL
dbt_watsonx_presto-0.1.2.dist-info/top_level.txt
dbt_watsonx_presto-0.1.2.dist-info/RECORD
