Metadata-Version: 2.4
Name: dbt-watsonx-presto
Version: 0.1.2
Summary: The Presto adapter plugin for dbt (data build tool)
Home-page: https://github.com/IBM/dbt-watsonx-presto
Author: IBM watsonx.data
Classifier: Development Status :: 5 - Production/Stable
Classifier: Operating System :: MacOS :: MacOS X
Classifier: Operating System :: Microsoft :: Windows
Classifier: Operating System :: POSIX :: Linux
Classifier: Programming Language :: Python :: 3.9
Classifier: Programming Language :: Python :: 3.10
Classifier: Programming Language :: Python :: 3.11
Classifier: Programming Language :: Python :: 3.12
Requires-Python: >=3.9
License-File: LICENSE
Requires-Dist: dbt-core>=1.8.0
Requires-Dist: presto-python-client==0.8.4
Dynamic: author
Dynamic: classifier
Dynamic: description
Dynamic: description-content-type
Dynamic: home-page
Dynamic: license-file
Dynamic: requires-dist
Dynamic: requires-python
Dynamic: summary
